LICENSE
MANIFEST.in
README.rst
setup.cfg
setup.py
django_fbauth_templatetag.egg-info/PKG-INFO
django_fbauth_templatetag.egg-info/SOURCES.txt
django_fbauth_templatetag.egg-info/dependency_links.txt
django_fbauth_templatetag.egg-info/not-zip-safe
django_fbauth_templatetag.egg-info/requires.txt
django_fbauth_templatetag.egg-info/top_level.txt
fbauth/__init__.py
fbauth/apps.py
fbauth/constants.py
fbauth/settings.py
fbauth/strings.py
fbauth/locale/es_PE/LC_MESSAGES/django.po
fbauth/static/fbauth/css/fbauth.css
fbauth/static/fbauth/html/channel.html
fbauth/static/fbauth/images/facebook-logo.png
fbauth/static/fbauth/js/check-jquery.js
fbauth/static/fbauth/js/fbauth.js
fbauth/static/fbauth/js/utils.js
fbauth/templates/fbauth/button.html
fbauth/templates/fbauth/css.html
fbauth/templatetags/__init__.py
fbauth/templatetags/fbauth.py