Metadata-Version: 1.1
Name: django-fbauth-templatetag
Version: 0.2
Summary: Django app that comes with a simple template tag to place a Facebook log-in button in your template
Home-page: https://github.com/hellhound/django-fbauth-templatetag
Author: Jean-Pierre Chauvel
Author-email: jchauvel@gmail
License: BSD
Platform: UNKNOWN
Classifier: Environment :: Web Environment
Classifier: Framework :: Django
Classifier: Intended Audience :: Developers
Classifier: License :: OSI Approved :: BSD License
Classifier: Operating System :: OS Independent
Classifier: Programming Language :: Python
Classifier: Topic :: Internet :: WWW/HTTP
Classifier: Topic :: Internet :: WWW/HTTP :: Dynamic Content
